pycolate/CoarseGraining.py
pycolate/Percolation.py
pycolate/__init__.py
pycolate/grid_engine.py
pycolate-0.0.42.dist-info/LICENSE
pycolate-0.0.42.dist-info/METADATA
pycolate-0.0.42.dist-info/WHEEL
pycolate-0.0.42.dist-info/top_level.txt
pycolate-0.0.42.dist-info/RECORD
